<?xml version="1.0" encoding="UTF-8"?>
<objects serializationModel="Studio.02.03.00">
	<object class="EncodingSetting" id="{0bd59f2b-0528-445e-b140-2045ce10d5da}">
		<property name="encodingFormat">
			<value>3</value>
		</property>
		<property name="quality">
			<value>37</value>
		</property>
		<relationship name="platform">
			<destination>{1b8f648a-c0e1-4d56-958e-00114f72c34d}</destination>
		</relationship>
		<relationship name="encodable">
			<destination>{1b8f648a-c0e1-4d56-958e-00114f72c34d}</destination>
		</relationship>
	</object>
</objects>
